package/__init__.py
package/matching.py
package/superglue.py
package/superpoint.py
package/utils.py
superpoint_superglue/__init__.py
superpoint_superglue/matching.py
superpoint_superglue/superglue.py
superpoint_superglue/superpoint.py
superpoint_superglue/utils.py
superpoint_superglue-0.2.dist-info/METADATA
superpoint_superglue-0.2.dist-info/WHEEL
superpoint_superglue-0.2.dist-info/top_level.txt
superpoint_superglue-0.2.dist-info/RECORD
