Metadata-Version: 2.4
Name: superpoint_superglue
Version: 0.2
Summary: superpoint_superglue
Author: xx
Dynamic: author
Dynamic: summary
